{
	"class" : {
		"on:" : "SantiagoBragagnolo 9/30/2014 14:04" },
	"instance" : {
		"hasLeft:" : "SantiagoBragagnolo 2/27/2013 14:54",
		"minimumPrecision" : "SantiagoBragagnolo 10/9/2012 11:53",
		"nextEncodedByte" : "SantiagoBragagnolo 10/20/2014 22:03",
		"nextEncodedDuration" : "SantiagoBragagnolo 10/20/2014 22:03",
		"nextEncodedFloat32" : "SantiagoBragagnolo 9/14/2015 16:13",
		"nextEncodedFloat64" : "SantiagoBragagnolo 10/20/2014 22:03",
		"nextEncodedInt16" : "SantiagoBragagnolo 10/20/2014 22:03",
		"nextEncodedInt32" : "SantiagoBragagnolo 10/20/2014 22:04",
		"nextEncodedInt64" : "SantiagoBragagnolo 10/20/2014 22:04",
		"nextEncodedInt8" : "SantiagoBragagnolo 10/20/2014 22:04",
		"nextEncodedString" : "SantiagoBragagnolo 10/20/2014 22:04",
		"nextEncodedTime" : "SantiagoBragagnolo 10/20/2014 22:04",
		"nextEncodedUint16" : "SantiagoBragagnolo 10/20/2014 22:04",
		"nextEncodedUint32" : "SantiagoBragagnolo 10/20/2014 22:04",
		"nextEncodedUint64" : "SantiagoBragagnolo 10/20/2014 22:04",
		"nextEncodedUint8" : "SantiagoBragagnolo 10/20/2014 22:05",
		"resetBuffers" : "SantiagoBragagnolo 10/1/2014 12:16",
		"stream:" : "SantiagoBragagnolo 10/9/2012 09:59",
		"verifyDataAvailability" : "SantiagoBragagnolo 1/30/2013 16:20",
		"verifyDataAvailability:" : "SantiagoBragagnolo 10/20/2014 22:05" } }
