{
	"class" : {
		"serve:" : "SantiagoBragagnolo 10/29/2014 19:42" },
	"instance" : {
		"deleteParam" : "SantiagoBragagnolo 10/29/2014 19:41",
		"domain:" : "SantiagoBragagnolo 10/29/2014 19:43",
		"getParam:for:" : "SantiagoBragagnolo 11/4/2014 13:57",
		"getParamNames:" : "SantiagoBragagnolo 11/4/2014 13:47",
		"getPid:" : "SantiagoBragagnolo 11/4/2014 13:47",
		"getSystemState:" : "SantiagoBragagnolo 11/3/2014 20:06",
		"getTopicTypes:" : "SantiagoBragagnolo 11/4/2014 13:47",
		"getUri:" : "SantiagoBragagnolo 11/4/2014 13:47",
		"hasParam:named:" : "SantiagoBragagnolo 11/3/2014 21:12",
		"initialize" : "SantiagoBragagnolo 10/30/2014 17:41",
		"lookupNode:named:" : "SantiagoBragagnolo 11/4/2014 13:47",
		"lookupService:named:" : "SantiagoBragagnolo 11/3/2014 21:14",
		"perform:withArguments:" : "SantiagoBragagnolo 11/4/2014 13:49",
		"registerPublisher:to:with:andCallerUri:" : "SantiagoBragagnolo 11/4/2014 13:48",
		"registerService:at:for:with:" : "SantiagoBragagnolo 11/4/2014 13:48",
		"registerSubscriber:to:with:andCallerUri:" : "SantiagoBragagnolo 10/29/2014 21:53",
		"resolveNameFor:" : "SantiagoBragagnolo 11/3/2014 15:27",
		"setParam:named:with:" : "SantiagoBragagnolo 11/3/2014 21:16",
		"start" : "SantiagoBragagnolo 11/4/2014 13:52",
		"subscribeParam:callingBack:for:" : "SantiagoBragagnolo 11/3/2014 21:17",
		"unimplemented" : "SantiagoBragagnolo 10/29/2014 19:31",
		"unregisterPublisher:from:andCallerUri:" : "SantiagoBragagnolo 10/29/2014 19:04",
		"unregisterService:at:for:" : "SantiagoBragagnolo 11/4/2014 13:52",
		"unregisterSubscriber:from:andCallerUri:" : "SantiagoBragagnolo 10/29/2014 19:04",
		"unsubscribeParam:callingBack:for:" : "SantiagoBragagnolo 11/3/2014 21:18" } }
